AUTHORS
LICENSE
MANIFEST.in
README.md
setup.py
rubyenv/__init__.py
rubyenv/_version.py
rubyenv/app.py
rubyenv.egg-info/PKG-INFO
rubyenv.egg-info/SOURCES.txt
rubyenv.egg-info/dependency_links.txt
rubyenv.egg-info/entry_points.txt
rubyenv.egg-info/requires.txt
rubyenv.egg-info/top_level.txt