Metadata-Version: 1.1
Name: rubyenv
Version: 0.3
Summary: manage ruby in your virtualenv
Home-page: http://github.com/twang817/rubyenv
Author: Tommy Wang
Author-email: twang@august8.net
License: MIT
Download-URL: https://github.com/twang817/rubyenv/tarball/0.3
Keywords: ruby virtualenv
Platform: any
Classifier: Development Status :: 4 - Beta
Classifier: Intended Audience :: Developers
